yt_parallel/__init__.py
yt_parallel/main.py
yt_parallel-1.0.1.dist-info/METADATA
yt_parallel-1.0.1.dist-info/WHEEL
yt_parallel-1.0.1.dist-info/entry_points.txt
yt_parallel-1.0.1.dist-info/top_level.txt
yt_parallel-1.0.1.dist-info/RECORD
