Metadata-Version: 2.4
Name: yt-parallel
Version: 1.0.1
Summary: Downloads and processes parallel YouTube subtitles with eSpeak IPA generation.
Author-email: "@readwithai" <talwrii@gmail.com>
Project-URL: Homepage, https://github.com/talwrii/yt-parallel
Project-URL: Repository, https://github.com/talwrii/yt-parallel
Classifier: Programming Language :: Python :: 3
Classifier: License :: OSI Approved :: MIT License
Classifier: Operating System :: OS Independent
Classifier: Topic :: Text Processing
Classifier: Topic :: Multimedia :: Video
Classifier: Development Status :: 3 - Alpha
